setup.py
distributions11111/Binomialdistribution.py
distributions11111/Gaussiandistribution.py
distributions11111/Generaldistribution.py
distributions11111/__init__.py
distributions11111.egg-info/PKG-INFO
distributions11111.egg-info/SOURCES.txt
distributions11111.egg-info/dependency_links.txt
distributions11111.egg-info/not-zip-safe
distributions11111.egg-info/top_level.txt